dj_qiyu_tpl/__init__.py
dj_qiyu_tpl/admin.py
dj_qiyu_tpl/apps.py
dj_qiyu_tpl/fields/__init__.py
dj_qiyu_tpl/fields/custom.py
dj_qiyu_tpl/fields/test_line.py
dj_qiyu_tpl/forms/__init__.py
dj_qiyu_tpl/forms/custom.py
dj_qiyu_tpl/migrations/__init__.py
dj_qiyu_tpl/models.py
dj_qiyu_tpl/rst/__init__.py
dj_qiyu_tpl/rst/rst.py
dj_qiyu_tpl/static/dj_qiyu_tpl/img/gongan.png
dj_qiyu_tpl/static/dj_qiyu_tpl/js/app_doc_node.js
dj_qiyu_tpl/static/dj_qiyu_tpl/vendor/bulma/bulma-rtl.css
dj_qiyu_tpl/static/dj_qiyu_tpl/vendor/bulma/bulma-rtl.css.map
dj_qiyu_tpl/static/dj_qiyu_tpl/vendor/bulma/bulma-rtl.min.css
dj_qiyu_tpl/static/dj_qiyu_tpl/vendor/bulma/bulma.css
dj_qiyu_tpl/static/dj_qiyu_tpl/vendor/bulma/bulma.css.map
dj_qiyu_tpl/static/dj_qiyu_tpl/vendor/bulma/bulma.min.css
dj_qiyu_tpl/static/dj_qiyu_tpl/vendor/darkreader/darkreader.js
dj_qiyu_tpl/static/dj_qiyu_tpl/vendor/fa/css/font-awesome.css
dj_qiyu_tpl/static/dj_qiyu_tpl/vendor/fa/css/font-awesome.css.map
dj_qiyu_tpl/static/dj_qiyu_tpl/vendor/fa/css/font-awesome.min.css
dj_qiyu_tpl/static/dj_qiyu_tpl/vendor/fa/fonts/FontAwesome.otf
dj_qiyu_tpl/static/dj_qiyu_tpl/vendor/fa/fonts/fontawesome-webfont.eot
dj_qiyu_tpl/static/dj_qiyu_tpl/vendor/fa/fonts/fontawesome-webfont.svg
dj_qiyu_tpl/static/dj_qiyu_tpl/vendor/fa/fonts/fontawesome-webfont.ttf
dj_qiyu_tpl/static/dj_qiyu_tpl/vendor/fa/fonts/fontawesome-webfont.woff
dj_qiyu_tpl/static/dj_qiyu_tpl/vendor/fa/fonts/fontawesome-webfont.woff2
dj_qiyu_tpl/static/dj_qiyu_tpl/vendor/remixicon/remixicon.css
dj_qiyu_tpl/static/dj_qiyu_tpl/vendor/remixicon/remixicon.eot
dj_qiyu_tpl/static/dj_qiyu_tpl/vendor/remixicon/remixicon.less
dj_qiyu_tpl/static/dj_qiyu_tpl/vendor/remixicon/remixicon.svg
dj_qiyu_tpl/static/dj_qiyu_tpl/vendor/remixicon/remixicon.symbol.svg
dj_qiyu_tpl/static/dj_qiyu_tpl/vendor/remixicon/remixicon.ttf
dj_qiyu_tpl/static/dj_qiyu_tpl/vendor/remixicon/remixicon.woff
dj_qiyu_tpl/static/dj_qiyu_tpl/vendor/remixicon/remixicon.woff2
dj_qiyu_tpl-0.4.1.dist-info/LICENSE
dj_qiyu_tpl-0.4.1.dist-info/WHEEL
dj_qiyu_tpl-0.4.1.dist-info/METADATA
dj_qiyu_tpl-0.4.1.dist-info/RECORD
