Metadata-Version: 2.1
Name: dj-qiyu-tpl
Version: 0.4.1
Summary: Template for internal use
Home-page: https://www.qiyutech.tech/
Author: dev
Author-email: dev@qiyutech.tech
Requires-Python: >=3.9,<4.0
Classifier: Programming Language :: Python :: 3
Classifier: Programming Language :: Python :: 3.9
Requires-Dist: django (>=3.2.4,<3.3)
Requires-Dist: django-qiyu-utils (>=0.3.9,<0.4)
Requires-Dist: docutils (>=0.16,<0.18)
Requires-Dist: pygments (>=2.8,<3.0)
